flet_core/__init__.py
flet_core/alert_dialog.py
flet_core/alignment.py
flet_core/animated_switcher.py
flet_core/animation.py
flet_core/app_bar.py
flet_core/audio.py
flet_core/banner.py
flet_core/border.py
flet_core/border_radius.py
flet_core/bottom_sheet.py
flet_core/buttons.py
flet_core/callable_control.py
flet_core/card.py
flet_core/checkbox.py
flet_core/circle_avatar.py
flet_core/client_storage.py
flet_core/clipboard.py
flet_core/colors.py
flet_core/column.py
flet_core/connection.py
flet_core/constrained_control.py
flet_core/container.py
flet_core/control.py
flet_core/control_event.py
flet_core/datatable.py
flet_core/divider.py
flet_core/drag_target.py
flet_core/draggable.py
flet_core/dropdown.py
flet_core/elevated_button.py
flet_core/embed_json_encoder.py
flet_core/event.py
flet_core/event_handler.py
flet_core/file_picker.py
flet_core/filled_button.py
flet_core/filled_tonal_button.py
flet_core/flet_app.py
flet_core/floating_action_button.py
flet_core/focus.py
flet_core/form_field_control.py
flet_core/gesture_detector.py
flet_core/gradients.py
flet_core/grid_view.py
flet_core/haptic_feedback.py
flet_core/icon.py
flet_core/icon_button.py
flet_core/icons.py
flet_core/image.py
flet_core/list_tile.py
flet_core/list_view.py
flet_core/local_connection.py
flet_core/margin.py
flet_core/markdown.py
flet_core/matplotlib_chart.py
flet_core/navigation_bar.py
flet_core/navigation_rail.py
flet_core/outlined_button.py
flet_core/padding.py
flet_core/page.py
flet_core/plotly_chart.py
flet_core/popup_menu_button.py
flet_core/progress_bar.py
flet_core/progress_ring.py
flet_core/protocol.py
flet_core/querystring.py
flet_core/radio.py
flet_core/radio_group.py
flet_core/ref.py
flet_core/responsive_row.py
flet_core/row.py
flet_core/semantics.py
flet_core/session_storage.py
flet_core/shader_mask.py
flet_core/shake_detector.py
flet_core/slider.py
flet_core/snack_bar.py
flet_core/stack.py
flet_core/switch.py
flet_core/tabs.py
flet_core/template_route.py
flet_core/text.py
robocorp_flet_core-0.4.2.dist-info/METADATA
robocorp_flet_core-0.4.2.dist-info/WHEEL
robocorp_flet_core-0.4.2.dist-info/RECORD
